setup.py
holmesalf/__init__.py
holmesalf/version.py
holmesalf/wrapper.py
holmesalf.egg-info/PKG-INFO
holmesalf.egg-info/SOURCES.txt
holmesalf.egg-info/dependency_links.txt
holmesalf.egg-info/entry_points.txt
holmesalf.egg-info/requires.txt
holmesalf.egg-info/top_level.txt
tests/__init__.py
tests/base.py
tests/test_version.py
tests/test_wrapper.py