Metadata-Version: 1.1
Name: holmesalf
Version: 0.1.3
Summary: holmes-alf is a wrapper for OAuth 2 synchronous (based on alf) and asynchronous (based on the tornado-alf) clients that can bu used in holmes.
Home-page: https://github.com/holmes-app/holmes-alf
Author: Pablo Aguiar
Author-email: scorphus@gmail.com
License: MIT
Keywords: alf client client_credentials holmes oauth requests tornado
Platform: UNKNOWN
Classifier: Development Status :: 4 - Beta
Classifier: Intended Audience :: Developers
Classifier: License :: OSI Approved :: MIT License
Classifier: Natural Language :: English
Classifier: Operating System :: Unix
Classifier: Operating System :: OS Independent
Classifier: Programming Language :: Python :: 2.7
Classifier: Programming Language :: Python :: 3.4
